{
   "CameraForward" : [ "c:leftstick_yneg", "key:e", "key:unknown" ],
   "CameraBackward" : [ "c:leftstick_ypos", "key:d", "key:unknown" ],
   "CameraLeft" : [ "c:leftstick_xneg", "key:s", "key:unknown" ],
   "CameraRight" : [ "c:leftstick_xpos", "key:f", "key:unknown" ],
   "CameraCenter" : [ "key:a" ],

   "CameraRotateLeft" : [ "c:rightstick_xpos", "key:l" ],
   "CameraRotateRight" : [ "c:rightstick_xneg", "key:j" ],
   
   "CameraZoomIn" : [ "c:rightstick_yneg", "key:'", "mouse:wheel_ypos" ],
   "CameraZoomOut" : [ "c:rightstick_ypos", "key:;", "mouse:wheel_yneg" ],

   "Action1" : [ "c:a", "key:i", "mouse:left" ],
   "ActionCancel" : [ "c:b", "key:m", "mouse:right" ],
   "ContextMenu" : [ "c:x", "key:n" ],
   "UICancel" : [ "c:b", "key:u" ],
   "UIEndTurn" : [ "c:b", "key:q" ],
   
   "DestructionToggle" : [ "c:dpad_right", "key:c" ],
   "QueueCommand" : [ "key:x" ],

   "HighlightCharacters" : [ "key:tab" ],
   "ToggleSneak" : [ "c:dpad_down", "key:b" ],
   "ToggleCombatMode" : [ "key:v" ],
   "TogglePresentation" : [ "key:." ],
   "ToggleTacticalCamera" : [ "c:dpad_up", "key:o" ],

   "ToggleEquipment" : [ "key:g" ],
   "ToggleInventory" : [ "key:h" ],
   "ToggleCraft" : [ "key:w" ],
   "ToggleSkills" : [ "c:y", "key:z" ],
   "ToggleJournal" : [ "key:," ],
   "ToggleMap" : [ "c:back", "c:touch_press", "key:r", "key:unknown" ], 
   "ToggleHomestead" : [ "key:/" ],

   "UIHotBarNext" : [ "c:rightshoulder", "key:y" ],
   "UIHotBarPrev" : [ "c:leftshoulder", "key:t" ],

   "UISelectChar1" : [ "key:k", "key:F1" ],
   "UISelectChar2" : [ "key:p", "key:F2" ],
   "UISelectChar3" : [ "key:F3" ],
   "UISelectChar4" : [ "key:F4" ],
   
   "UISelectSlot1" : [ "key:1" ],
   "UISelectSlot2" : [ "key:2" ],
   "UISelectSlot3" : [ "key:3" ],
   "UISelectSlot4" : [ "key:4" ],
   "UISelectSlot5" : [ "key:5" ],
   "UISelectSlot6" : [ "key:6" ],
   "UISelectSlot7" : [ "key:7" ],
   "UISelectSlot8" : [ "key:8" ],
   "UISelectSlot9" : [ "key:9", "key:kp_9" ],
   "UISelectSlot0" : [ "key:0" ],

   "UISelectSlot11": [ "key:-" ],
   "UISelectSlot12": [ "key:=" ],
   "UITakeAll": [ "key:space" ],
   "SkipVideo": [ "key:escape" ],
   "ToggleInGameMenu": [ "key:escape" ],
   "ShowSneakCones": [ "key:lshift", "key:[" ],
   "ShowWorldTooltips": [ "key:lalt" ],
   "QuickSave": [ "key:F5" ],
   "QuickLoad": [ "key:F8"],
   
   "SplitItemToggle" : [ "key:lshift", "key:rshift" ],
   "RotateItemLeft" : [ "c:rightshoulder", "key:unknown" ],
   "RotateItemRight" : [ "c:leftshoulder", "key:unknown" ],
   "ToggleInputMode" : [ "c:leftstick", "key:unknown" ],
   "ToggleGMInventory" : [],
   "ToggleCharacterPane" : [],
   "CameraToggleMouseRotate" : [],
   "CycleCharactersNext" : [],
   "CycleCharactersPrev" : [],
   "GMKillResurrect" : [],
   "GMNormalAlignMode" : [],
   "GMSetHealth" : [],
   "Ping" : [],
   "ShowChat" : [],
   "SwitchGMMode" : [],
   "ToggleGMItemGeneratorPane" : [],
   "ToggleGMMiniMap" : [],
   "ToggleGMMoodPanel" : [],
   "ToggleGMPause" : [],
   "ToggleGMRewardPanel" : [],
   "ToggleGMShroud" : [],
   "ToggleInfo" : [],
   "ToggleManageTarget" : [],
   "ToggleMonsterSelect" : [],
   "ToggleOverviewMap" : [],
   "TogglePartyManagement" : [],
   "ToggleRecipes" : [],
   "ToggleReputationPanel" : [],
   "ToggleRollPanel" : [],
   "ToggleSetStartPoint" : [],
   "ToggleStatusPanel" : [],
   "ToggleSurfacePainter" : [],
   "ToggleVignette" : [],
   "UIRefresh" : [],
   "UIToggleActions" : []
}
